mixing/__init__.py
mixing/video/__init__.py
mixing/video/video_files.py
mixing/video/video_util.py
mixing-0.0.4.dist-info/LICENSE
mixing-0.0.4.dist-info/METADATA
mixing-0.0.4.dist-info/WHEEL
mixing-0.0.4.dist-info/top_level.txt
mixing-0.0.4.dist-info/RECORD
