Metadata-Version: 2.1
Name: mixing
Version: 0.0.4
Summary: Tools for video and audio editing
Home-page: https://github.com/thorwhalen/mixing
Author: Thor Whalen
License: mit
Platform: any
License-File: LICENSE
Requires-Dist: moviepy
Requires-Dist: config2py
Requires-Dist: dol
Requires-Dist: opencv-python
Provides-Extra: testing
